residuals/__init__.py
residuals/config.py
residuals/metadata.py
residuals/py.typed
residuals/readme.py
residuals/residuals.py
residuals/tokenization.py
residuals-0.2.1.dist-info/METADATA
residuals-0.2.1.dist-info/WHEEL
residuals-0.2.1.dist-info/licenses/LICENSE
residuals-0.2.1.dist-info/RECORD
