Metadata-Version: 2.4
Name: residuals
Version: 0.2.1
Summary: Instruction residuals (task vectors) for efficient LLM continuous pre-training
Project-URL: Homepage, https://github.com/omarkamali/residuals
Project-URL: Documentation, https://github.com/omarkamali/residuals#readme
Project-URL: Repository, https://github.com/omarkamali/residuals
Project-URL: Issues, https://github.com/omarkamali/residuals/issues
Author-email: Omar Kamali <residuals@omarkama.li>
Maintainer-email: Omar Kamali <residuals@omarkama.li>
License: MIT
License-File: LICENSE
Keywords: continual-learning,continuous-pretraining,cpt,instruction-tuning,llm,model-merging,sft,task-vectors
Classifier: Development Status :: 4 - Beta
Classifier: Intended Audience :: Developers
Classifier: Intended Audience :: Science/Research
Classifier: License :: OSI Approved :: MIT License
Classifier: Programming Language :: Python :: 3
Classifier: Programming Language :: Python :: 3.9
Classifier: Programming Language :: Python :: 3.10
Classifier: Programming Language :: Python :: 3.11
Classifier: Programming Language :: Python :: 3.12
Classifier: Programming Language :: Python :: 3.13
Classifier: Programming Language :: Python :: 3.14
Classifier: Topic :: Scientific/Engineering :: Artificial Intelligence
Requires-Python: >=3.9
Requires-Dist: huggingface-hub>=0.24.0
Requires-Dist: safetensors>=0.4.2
Requires-Dist: torch>=2.0.0
Requires-Dist: transformers>=4.30.0
Provides-Extra: dev
Requires-Dist: mypy>=1.0.0; extra == 'dev'
Requires-Dist: pytest-cov>=4.0.0; extra == 'dev'
Requires-Dist: pytest>=7.0.0; extra == 'dev'
Requires-Dist: ruff>=0.1.0; extra == 'dev'
Provides-Extra: gpu
Requires-Dist: accelerate>=0.26.0; extra == 'gpu'
